{
  "@context": "http://iiif.io/api/presentation/3/context.json",
  "id": "https://kayleighv.github.io/timestamps/interview-with-alice-walker/canvas-1/canvas/environment.json",
  "type": "AnnotationPage",
  "label": "Environment",
  "items": [
    {
      "@context": "http://www.w3.org/ns/anno.jsonld",
      "id": "https://kayleighv.github.io/timestamps/interview-with-alice-walker/canvas-1/canvas/environment-annotation-1.json",
      "type": "Annotation",
      "motivation": [
        "supplementing",
        "commenting"
      ],
      "body": {
        "type": "TextualBody",
        "value": "A fan interrupts to tell Walker how much she values her story \"To Hell With Dying\".",
        "format": "text/plain"
      },
      "target": {
        "source": "https://kayleighv.github.io/timestamps/interview-with-alice-walker/canvas-1/canvas",
        "selector": {
          "type": "RangeSelector",
          "t": "1160.0,1185.0"
        }
      }
    }
  ]
}